Workbook

Sheet META
A1: project_code | B1: version_code | C1: scenario_code | D1: version_date | E1: status | F1: currency | G1: wacc
A2: NCT.DEMO | B2: V1 | C2: BASE | D2: 2026-06-16 | E2: DRAFT | F2: RM | G2: 0.1

Sheet PHASE
A1: code | B1: phase_name | C1: product_type | D1: nda_acre | E1: plot_ratio | F1: gfa | G1: efficiency | H1: nfa | I1: avg_unit_size | J1: units | K1: construction_months
A2: P1 | B2: Phase 1 — High-rise Resi | C2: High-rise Residential | D2: 4 | E2: 3.5 | F2: =D2*43560*E2 | G2: 0.78 | H2: =F2*G2 | I2: 900 | J2: =ROUND(H2/I2,0) | K2: 30

Sheet SALES
A1: code | B1: line_name | C1: basis | D1: qty | E1: rate | F1: amount | H1: Net GDV = | I1: =SUM(tbl_SALES[amount])
A2: S.RESI | B2: Resi open market | C2: NFA x psf | D2: 475675.2 | E2: 650 | F2: 309188880
A3: S.BUMI | B3: Bumi discount | C3: on bumi units | F3: -6492966.5
A4: S.AFFORD | B4: Affordable subsidy | C4: cross-subsidy | F4: -28724700
A5: S.CARPARK | B5: Car park (extra bays) | C5: bays x price | D5: 80 | E5: 45000 | F5: 3600000

Sheet COST
A1: code | B1: pillar | C1: category | D1: report_no | E1: item_name | F1: budget | G1: committed | H1: actual | I1: variance | J1: note | L1: ROLLUP (display only — SUMIFS)
A2: L.PURCHASE | B2: P1 | C2: Land | D2: 1.1 | E2: Land Purchase Price | F2: 12000000 | G2: 0 | H2: 0 | I2: =F2-H2 | L2: P1 · Land | M2: =SUMIFS(tbl_COST[budget],tbl_COST[pillar],"P1")
A3: L.STAMP | B3: P1 | C3: Land | D3: 1.2 | E3: Stamp Duty | F3: 464000 | G3: 0 | H3: 0 | I3: =F3-H3 | L3: P2 · Construction | M3: =SUMIFS(tbl_COST[budget],tbl_COST[pillar],"P2")
A4: L.LEGAL | B4: P1 | C4: Land | D4: 1.3 | E4: Legal Fees | F4: 120000 | G4: 0 | H4: 0 | I4: =F4-H4 | L4: P3 · Infra | M4: =SUMIFS(tbl_COST[budget],tbl_COST[pillar],"P3")
A5: L.CONV | B5: P1 | C5: Land | D5: 1.4 | E5: Conversion Premium | F5: 500000 | G5: 0 | H5: 0 | I5: =F5-H5 | L5: P4 · Professional | M5: =SUMIFS(tbl_COST[budget],tbl_COST[pillar],"P4")
A6: L.HOLD | B6: P1 | C6: Land | D6: 1.5 | E6: Holding Interest | F6: 400000 | G6: 0 | H6: 0 | I6: =F6-H6 | L6: P5 · Finance+Mkt | M6: =SUMIFS(tbl_COST[budget],tbl_COST[pillar],"P5")
A7: L.VAL | B7: P1 | C7: Land | D7: 1.6 | E7: Valuation + Misc | F7: 48000 | G7: 0 | H7: 0 | I7: =F7-H7 | L7: GDC | M7: =SUM(M2:M6)
A8: C.PILE | B8: P2 | C8: Construction | D8: 2.1 | E8: Piling Works | F8: 3200000 | G8: 0 | H8: 0 | I8: =F8-H8 | L8: Net GDV | M8: =SUM(tbl_SALES[amount])
A9: C.SUB | B9: P2 | C9: Construction | D9: 2.2 | E9: Substructure | F9: 2600000 | G9: 0 | H9: 0 | I9: =F9-H9 | L9: PBT | M9: =M8-M7
A10: C.SUPER_CS | B10: P2 | C10: Construction | D10: 2.3 | E10: Superstructure C&S | F10: 15200000 | G10: 0 | H10: 0 | I10: =F10-H10 | L10: Margin | M10: =M9/M8
A11: C.ARCH | B11: P2 | C11: Construction | D11: 2.4 | E11: Architectural Works | F11: 8800000 | G11: 0 | H11: 0 | I11: =F11-H11
A12: C.MEP_MECH | B12: P2 | C12: Construction | D12: 2.5 | E12: M&E Mechanical | F12: 3600000 | G12: 0 | H12: 0 | I12: =F12-H12
A13: C.MEP_ELEC | B13: P2 | C13: Construction | D13: 2.6 | E13: M&E Electrical | F13: 3000000 | G13: 0 | H13: 0 | I13: =F13-H13
A14: C.PLUMB | B14: P2 | C14: Construction | D14: 2.7 | E14: Plumbing & Sanitary | F14: 1600000 | G14: 0 | H14: 0 | I14: =F14-H14
A15: C.LANDSC | B15: P2 | C15: Construction | D15: 2.8 | E15: Landscaping (Internal) | F15: 800000 | G15: 0 | H15: 0 | I15: =F15-H15
A16: C.PRELIM | B16: P2 | C16: Construction | D16: 2.9 | E16: Preliminaries | F16: 3104000 | G16: 0 | H16: 0 | I16: =F16-H16
A17: C.CONT | B17: P2 | C17: Construction | D17: 2.10 | E17: Contingency | F17: 2095200 | G17: 0 | H17: 0 | I17: =F17-H17
A18: I.ROAD_INT | B18: P3 | C18: Infra | D18: 3.1 | E18: Internal Roads | F18: 1400000 | G18: 0 | H18: 0 | I18: =F18-H18
A19: I.ROAD_EXT | B19: P3 | C19: Infra | D19: 3.2 | E19: External Road (JKR) | F19: 700000 | G19: 0 | H19: 0 | I19: =F19-H19
A20: I.DRAIN | B20: P3 | C20: Infra | D20: 3.3 | E20: Drainage (JPS) | F20: 880000 | G20: 0 | H20: 0 | I20: =F20-H20
A21: I.TNB | B21: P3 | C21: Infra | D21: 3.4 | E21: TNB Substation | F21: 600000 | G21: 0 | H21: 0 | I21: =F21-H21
A22: I.WATER | B22: P3 | C22: Infra | D22: 3.5 | E22: Water Supply | F22: 360000 | G22: 0 | H22: 0 | I22: =F22-H22
... A42: F.INS | B42: P5 | C42: Finance | D42: 5.8 | E42: Insurance (CAR/PI/PL) | F42: 263995.2 | G42: 0 | H42: 0 | I42: =F42-H42

Sheet CURVE
A1: code | B1: curve_type | C1: Y0 | D1: Y1 | E1: Y2 | F1: Y3 | G1: Y4 | H1: sum_check
A2: CV.SPEND | B2: spend | C2: 0.1 | D2: 0.3 | E2: 0.35 | F2: 0.2 | G2: 0.05 | H2: =SUM(C2:G2)
A3: CV.COLLECT | B3: collection | C3: 0.03 | D3: 0.2 | E3: 0.35 | F3: 0.3 | G3: 0.12 | H3: =SUM(C3:G3)
A4: CV.BILLING | B4: billing | C4: 0.1 | D4: 0.3 | E4: 0.35 | F4: 0.2 | G4: 0.05 | H4: =SUM(C4:G4)
A5: CV.ROS | B5: ros | C5: 0.2 | D5: 0.35 | E5: 0.25 | F5: 0.15 | G5: 0.05 | H5: =SUM(C5:G5)

Sheet CASHFLOW
A1: PHASE 1 CASH FLOW — sourced from tables
B3: (curves resolved from tbl_CURVE) | C3: Y0 | D3: Y1 | E3: Y2 | F3: Y3 | G3: Y4
B4: spend | C4: =INDEX(tbl_CURVE[Y0],MATCH("spend",tbl_CURVE[curve_type],0)) | D4: =INDEX(tbl_CURVE[Y1],MATCH("spend",tbl_CURVE[curve_type],0)) | E4: =INDEX(tbl_CURVE[Y2],MATCH("spend",tbl_CURVE[curve_type],0)) | F4: =INDEX(tbl_CURVE[Y3],MATCH("spend",tbl_CURVE[curve_type],0)) | G4: =INDEX(tbl_CURVE[Y4],MATCH("spend",tbl_CURVE[curve_type],0))
B5: collection | C5: =INDEX(tbl_CURVE[Y0],MATCH("collection",tbl_CURVE[curve_type],0)) | D5: =INDEX(tbl_CURVE[Y1],MATCH("collection",tbl_CURVE[curve_type],0)) | E5: =INDEX(tbl_CURVE[Y2],MATCH("collection",tbl_CURVE[curve_type],0)) | F5: =INDEX(tbl_CURVE[Y3],MATCH("collection",tbl_CURVE[curve_type],0)) | G5: =INDEX(tbl_CURVE[Y4],MATCH("collection",tbl_CURVE[curve_type],0))
B7: Land outflow (P1) | C7: =COST!M2 | D7: 0 | E7: 0 | F7: 0 | G7: 0
B8: Dev outflow (P2-P5) | C8: =(COST!$M$7-COST!$M$2)*C4 | D8: =(COST!$M$7-COST!$M$2)*D4 | E8: =(COST!$M$7-COST!$M$2)*E4 | F8: =(COST!$M$7-COST!$M$2)*F4 | G8: =(COST!$M$7-COST!$M$2)*G4
B9: Total outflow | C9: =C7+C8 | D9: =D7+D8 | E9: =E7+E8 | F9: =F7+F8 | G9: =G7+G8
B11: Revenue inflow | C11: =COST!$M$8*C5 | D11: =COST!$M$8*D5 | E11: =COST!$M$8*E5 | F11: =COST!$M$8*F5 | G11: =COST!$M$8*G5
B13: Net cash flow | C13: =C11-C9 | D13: =D11-D9 | E13: =E11-E9 | F13: =F11-F9 | G13: =G11-G9
B14: Cumulative | C14: =C13 | D14: =C14+D13 | E14: =D14+E13 | F14: =E14+F13 | G14: =F14+G13
B16: IRR | C16: =IRR(C13:G13)
B17: NPV @WACC | C17: =NPV(META!$G$2,D13:G13)+C13
B18: Peak funding | C18: =MIN(C14:G14)
B19: PBT | C19: =COST!M9
B20: Margin | C20: =COST!M10
